haven/__init__.py
haven/blueprint.py
haven/connection.py
haven/constants.py
haven/gevent_impl.py
haven/haven.py
haven/log.py
haven/mixins.py
haven/request.py
haven/thread_impl.py
haven/utils.py
haven/contrib/__init__.py
haven/contrib/websocket_gevent_impl.py
haven-2.0.4.dist-info/LICENSE
haven-2.0.4.dist-info/METADATA
haven-2.0.4.dist-info/WHEEL
haven-2.0.4.dist-info/top_level.txt
haven-2.0.4.dist-info/RECORD
