Metadata-Version: 2.1
Name: haven
Version: 2.0.4
Summary: flask's style binary server framework
Home-page: https://github.com/dantezhu/haven
Author: dantezhu
Author-email: dantezhu <zny2008@gmail.com>
License: MIT
Project-URL: Homepage, https://github.com/dantezhu/haven
Platform: any
Requires-Python: >=3
License-File: LICENSE
Requires-Dist: events
Requires-Dist: netkit
Requires-Dist: setproctitle
Requires-Dist: gevent
Requires-Dist: gevent-websocket
